weightGIS/Errors.py
weightGIS/FormatExternal.py
weightGIS/GeoLookup.py
weightGIS/IDAssignment.py
weightGIS/PlaceReference.py
weightGIS/__init__.py
weightGIS/Cleaning/FormatAsCsv.py
weightGIS/Cleaning/FormatCombine.py
weightGIS/Cleaning/FormatDataclasses.py
weightGIS/Cleaning/FormatLink.py
weightGIS/Cleaning/FormatNames.py
weightGIS/Cleaning/FormatPartitions.py
weightGIS/Cleaning/FormatRelational.py
weightGIS/Cleaning/FormatStandardise.py
weightGIS/Cleaning/__init__.py
weightGIS/weighting/AdjustWeights.py
weightGIS/weighting/AssignWeights.py
weightGIS/weighting/ConstructWeights.py
weightGIS/weighting/WeightExternal.py
weightGIS/weighting/__init__.py
weightGIS/weighting/Access/__init__.py
weightGIS/weighting/Access/access_weighted.py
weightGIS/weighting/Calculate/__init__.py
weightGIS/weighting/Calculate/exposures.py
weightGIS-0.15.0.dist-info/LICENSE
weightGIS-0.15.0.dist-info/METADATA
weightGIS-0.15.0.dist-info/WHEEL
weightGIS-0.15.0.dist-info/top_level.txt
weightGIS-0.15.0.dist-info/RECORD
