Metadata-Version: 2.1
Name: weightGIS
Version: 0.15.0
Summary: Weight ESRI shapefiles attributes
Home-page: UNKNOWN
Author: Samuel Baker
Author-email: samuelbaker.researcher@gmail.com
Maintainer: Samuel Baker
Maintainer-email: samuelbaker.researcher@gmail.com
License: MIT
Download-URL: https://github.com/sbaker-dev/weightGIS
Platform: UNKNOWN
Classifier: Programming Language :: Python :: 3.7
Classifier: Programming Language :: Python :: 3.8
Classifier: License :: OSI Approved :: MIT License
Requires-Python: >=3.6
Requires-Dist: csvObject
Requires-Dist: shapeObject
Requires-Dist: shapely
Requires-Dist: miscSupports
Requires-Dist: numpy
